madnansultan/__init__.py
madnansultan/cli.py
madnansultan/data.py
madnansultan/web.py
madnansultan-0.1.0.dist-info/licenses/LICENSE
madnansultan-0.1.0.dist-info/METADATA
madnansultan-0.1.0.dist-info/WHEEL
madnansultan-0.1.0.dist-info/entry_points.txt
madnansultan-0.1.0.dist-info/top_level.txt
madnansultan-0.1.0.dist-info/RECORD
