Metadata-Version: 2.4
Name: madnansultan
Version: 0.1.0
Summary: Portfolio of Muhammad Adnan Sultan as a Python package (CLI and Web)
Home-page: https://github.com/madnansultandotme
Author: Muhammad Adnan Sultan
Author-email: Muhammad Adnan Sultan <info.adnansultan@gmail.com>
Maintainer-email: Muhammad Adnan Sultan <info.adnansultan@gmail.com>
License: MIT
Project-URL: Homepage, https://github.com/madnansultandotme
Project-URL: Repository, https://github.com/madnansultandotme
Project-URL: Documentation, https://github.com/madnansultandotme#readme
Project-URL: Bug Tracker, https://github.com/madnansultandotme/issues
Keywords: portfolio,cli,web,resume,cv
Classifier: Development Status :: 4 - Beta
Classifier: Intended Audience :: Developers
Classifier: License :: OSI Approved :: MIT License
Classifier: Operating System :: OS Independent
Classifier: Programming Language :: Python :: 3
Classifier: Programming Language :: Python :: 3.7
Classifier: Programming Language :: Python :: 3.8
Classifier: Programming Language :: Python :: 3.9
Classifier: Programming Language :: Python :: 3.10
Classifier: Programming Language :: Python :: 3.11
Classifier: Programming Language :: Python :: 3.12
Classifier: Topic :: Software Development :: Libraries :: Python Modules
Classifier: Topic :: Internet :: WWW/HTTP :: Dynamic Content
Classifier: Topic :: Office/Business
Requires-Python: >=3.7
License-File: LICENSE
Requires-Dist: Flask>=2.0.0
Requires-Dist: reportlab>=3.6.0
Requires-Dist: click>=8.0.0
Dynamic: author
Dynamic: home-page
Dynamic: license-file
Dynamic: requires-python
